py4j_example/__init__.py
py4j_example/app.py
py4j_example/version.py
py4j_example/jars/Py4J-1.0-SNAPSHOT.jar
py4j_example/jars/py4j-0.10.9.7.jar
py4j_example-0.3.1.dist-info/LICENSE
py4j_example-0.3.1.dist-info/METADATA
py4j_example-0.3.1.dist-info/WHEEL
py4j_example-0.3.1.dist-info/top_level.txt
py4j_example-0.3.1.dist-info/RECORD
