Metadata-Version: 2.1
Name: py4j-example
Version: 0.3.1
License-File: LICENSE
